<PAMDataset>
  <PAMRasterBand band="1">
    <Histograms>
      <HistItem>
        <HistMin>-0.5</HistMin>
        <HistMax>1257.5</HistMax>
        <BucketCount>1258</BucketCount>
        <IncludeOutOfRange>1</IncludeOutOfRange>
        <Approximate>0</Approximate>
        <HistCounts>0|53677|28884|26272|24559|21638|23687|18469|20490|22877|20840|19044|20678|18479|22387|19513|18516|18967|17630|17194|21975|18098|17040|15915|17888|19390|16835|16290|16652|17076|17339|18858|15719|16691|14448|15219|15336|15502|15674|14938|14274|16273|14256|16279|16324|15853|16800|14753|14094|13596|14454|13746|13655|13619|12779|14452|13552|14067|13362|14558|13036|13034|11893|12947|12649|12442|11882|12385|12132|11173|11737|10527|10987|11695|10672|11539|10543|11023|10097|10776|11002|10897|10402|11404|9344|9737|9440|10376|9481|9927|9767|10418|9873|9128|9560|8957|9276|9621|9747|8850|10116|9828|8877|8998|8607|9151|8611|8841|8530|8281|8481|8262|8560|8455|9223|8114|7912|8369|8001|8368|8654|8308|7316|8133|7533|7494|7819|8527|8058|7600|7096|7657|7280|7139|7002|7240|6891|7326|6887|6671|6638|6738|7376|7137|6599|6718|6599|6612|6744|7109|6808|6440|6955|6822|6369|6504|6300|6421|6555|6467|6220|6056|6302|6552|6453|5875|5958|5772|6266|6174|6468|5668|5697|5895|6378|5519|5789|5762|5532|5572|5783|5703|5855|5429|5393|5689|5213|5016|5194|5058|5445|4905|4993|5446|5022|4945|4908|5060|4793|5149|5253|5135|4811|4709|4691|4630|5346|4672|4581|4628|4638|4609|4720|4860|4472|4810|4455|4613|4413|4308|4514|4298|4414|4217|4226|4313|4268|4319|4279|4172|4155|4056|4274|4438|4109|4058|4239|4091|4132|4267|3956|3965|4076|3896|3839|3980|3774|3974|3870|3802|3888|3769|3750|3651|3709|3793|3787|3803|3594|3624|3818|3815|3784|3586|3503|3655|3597|3585|3644|3921|3512|3524|3491|3387|3435|3385|3389|3456|3571|3285|3407|3403|3633|3539|3284|3348|3464|3225|3352|3551|3340|3349|3382|3336|3132|3465|3122|3371|3491|3169|3156|3069|3165|3073|3084|3167|3270|3112|3175|2967|3081|2928|2943|2999|3115|2909|2884|2849|2976|2873|2890|3077|2908|2877|2905|2831|2857|2755|2954|2842|3150|2790|3083|2786|2987|2860|2670|2709|2938|2760|2735|2581|2728|2735|2741|2683|2629|2749|2658|2682|2880|2639|2715|2600|2896|2722|2765|2566|2657|2482|2548|2607|2717|2590|2603|2453|2483|2535|2459|2438|2393|2558|2445|2462|2501|2288|2349|2433|2645|2321|2302|2347|2311|2383|2306|2249|2282|2216|2327|2350|2343|2313|2331|2325|2212|2318|2226|2255|2288|2177|2189|2143|2328|2279|2216|2115|2185|2315|2244|2228|2172|2261|2251|2079|2242|2185|2153|2130|1997|2016|2068|2076|2028|2000|1983|1945|1932|1882|1947|2026|1863|1908|1971|1891|1893|1913|1877|1999|1975|2026|1982|1938|1818|1891|1836|1894|1837|1861|1819|1852|1874|1757|1926|1756|1904|1790|1773|1803|1832|1736|1762|1871|1690|1841|1768|1685|1683|1679|1719|1661|1606|1718|1745|1758|1737|1741|1637|1693|1662|1662|1651|1681|1613|1657|1673|1645|1587|1550|1588|1651|1577|1555|1550|1586|1594|1658|1576|1572|1539|1557|1566|1487|1559|1491|1521|1602|1521|1530|1574|1500|1563|1586|1576|1508|1478|1504|1485|1569|1480|1505|1395|1463|1420|1452|1491|1450|1431|1405|1412|1420|1427|1484|1422|1436|1446|1351|1402|1402|1365|1362|1378|1450|1309|1353|1335|1339|1355|1289|1321|1314|1337|1294|1336|1291|1321|1294|1309|1263|1294|1268|1244|1284|1291|1194|1223|1262|1258|1218|1273|1256|1230|1285|1183|1181|1108|1200|1201|1153|1083|1196|1151|1143|1083|1103|1175|1130|1114|1107|1092|1140|1145|1027|1094|1093|1059|1132|1024|1039|1087|1080|1108|1012|1027|1108|1045|1004|1009|1069|1024|1013|1005|1050|1014|1044|1046|1009|963|1018|978|962|941|924|942|981|914|973|1007|956|973|962|890|878|973|935|942|947|905|941|922|913|935|847|900|891|903|869|905|881|962|865|895|827|903|865|857|864|862|845|905|845|828|839|896|818|828|833|860|863|854|876|827|831|885|823|830|866|825|769|843|843|785|828|812|784|797|824|762|778|799|823|761|738|769|762|775|726|771|771|724|786|753|782|736|707|789|764|744|747|809|715|785|725|732|719|705|739|756|710|712|749|703|720|695|689|698|758|661|655|728|731|670|671|660|687|668|695|720|697|680|702|685|663|649|691|669|719|723|693|671|665|635|662|658|639|663|644|649|609|694|647|617|663|645|636|623|703|663|626|633|583|628|633|607|633|563|625|613|621|612|587|596|580|613|628|633|584|569|581|604|597|618|593|565|568|540|603|557|592|529|558|551|551|585|582|562|548|545|568|553|545|541|565|556|545|558|543|538|548|535|514|520|544|535|522|508|539|538|501|492|473|503|532|532|521|497|531|490|506|544|490|530|527|454|450|481|504|478|467|487|464|480|494|494|486|453|494|470|449|471|480|440|495|435|447|437|429|435|439|421|431|448|426|426|440|438|410|450|434|453|421|421|398|433|423|426|438|417|428|453|425|386|418|390|397|386|375|414|414|407|425|423|407|413|383|373|385|426|406|390|352|380|349|385|376|383|358|377|364|367|363|359|377|332|348|377|378|362|344|353|375|360|366|370|354|353|348|340|372|335|319|324|333|342|364|348|307|363|327|353|350|386|359|345|363|359|362|356|377|358|358|391|306|330|343|304|343|330|326|343|350|358|345|320|333|331|319|324|368|357|297|312|324|316|300|308|346|311|324|330|318|326|250|274|312|301|312|287|280|269|318|290|308|320|294|293|291|286|294|279|288|281|266|275|277|287|265|301|269|253|252|241|257|258|292|237|274|274|261|258|245|278|243|235|240|217|246|206|225|270|213|254|260|247|235|236|244|237|209|213|226|223|223|204|217|223|245|240|218|230|220|236|212|201|199|193|226|225|231|201|201|233|216|201|200|238|201|174|209|225|338|245|251|224|215|221|213|217|216|219|242|192|227|231|229|200|211|179|198|223|204|191|307|209|216|200|190|200|181|219|219|210|209|200|215|180|170|208|212|201|199|199|178|198|219|224|164|190|175|181|177|184|206|186|176|186|194|164|171|188|190|220|173|169|209|182|179|174|186|160|162|162|163|174|192|199|180|178|198|171|196|138|162|170|141|164|158|192|157|170|187|184|183|150|163|194|167|151|157|149|178|190|161|165|150|130|167|155|127|121|159|142|172|148|142|148|156|144|149|119|141|103|116|120|108|133|148|150|138|131|111|121|106|131|128|132|121|119|122|114|101|118|117|101|108|120|115|146|134|117|124|122|124|126|133|137|108|117|142|142|113|203|507|119|197|138|143|127|131|148|125|131|137|141|146|167|169|443|7434</HistCounts>
      </HistItem>
    </Histograms>
    <Metadata>
      <MDI key="RepresentationType">THEMATIC</MDI>
      <MDI key="STATISTICS_COVARIANCES">58607.84358221382</MDI>
      <MDI key="STATISTICS_EXCLUDEDVALUES"></MDI>
      <MDI key="STATISTICS_MAXIMUM">1257</MDI>
      <MDI key="STATISTICS_MEAN">217.56870186314</MDI>
      <MDI key="STATISTICS_MINIMUM">1</MDI>
      <MDI key="STATISTICS_SKIPFACTORX">1</MDI>
      <MDI key="STATISTICS_SKIPFACTORY">1</MDI>
      <MDI key="STATISTICS_STDDEV">242.09056896586</MDI>
    </Metadata>
  </PAMRasterBand>
</PAMDataset>
